setup.py
bin/interest-calc
interest/__init__.py
interest/interest.py
interest_calc.egg-info/PKG-INFO
interest_calc.egg-info/SOURCES.txt
interest_calc.egg-info/dependency_links.txt
interest_calc.egg-info/not-zip-safe
interest_calc.egg-info/requires.txt
interest_calc.egg-info/top_level.txt