Metadata-Version: 1.0
Name: interest-calc
Version: 0.0.3
Summary: Very simple tool to compute interest gains over time in the command line.
Home-page: https://gitlab.com/PedroSilva/interest
Author: Pedro Silva
Author-email: ams.pedro@gmail.com
License: MIT
Platform: UNKNOWN
